flask_saasify/__init__.py
flask_saasify/admin/__init__.py
flask_saasify/admin/routes.py
flask_saasify/admin/templates/saasify_dashboard.html
flask_saasify/analytics/__init__.py
flask_saasify/analytics/models.py
flask_saasify/auth/__init__.py
flask_saasify/auth/forms.py
flask_saasify/auth/models.py
flask_saasify/auth/routes.py
flask_saasify/auth/templates/check_mail.html
flask_saasify/auth/templates/sign_in.html
flask_saasify/blog/__init__.py
flask_saasify/blog/models.py
flask_saasify/core/__init__.py
flask_saasify/core/templates/saasify_base.html
flask_saasify/core/templates/saasify_macros.html
Flask_SaaSify-0.0.5.dist-info/LICENSE
Flask_SaaSify-0.0.5.dist-info/METADATA
Flask_SaaSify-0.0.5.dist-info/WHEEL
Flask_SaaSify-0.0.5.dist-info/top_level.txt
Flask_SaaSify-0.0.5.dist-info/RECORD
