Metadata-Version: 2.1
Name: Flask-SaaSify
Version: 0.0.5
Summary: A Flask toolbox for rapidly building SaaS applications.
Home-page: https://github.com/koenvaneijk/flask-saasify
Author: Koen van Eijk
Author-email: vaneijk.koen@gmail.com
Classifier: Development Status :: 3 - Alpha
Classifier: Intended Audience :: Developers
Classifier: Topic :: Software Development :: Libraries :: Python Modules
Classifier: Programming Language :: Python :: 3
Classifier: Programming Language :: Python :: 3.7
Classifier: Programming Language :: Python :: 3.8
Classifier: Programming Language :: Python :: 3.9
Classifier: Programming Language :: Python :: 3.10
Requires-Python: >=3.7
License-File: LICENSE
Requires-Dist: Flask >=2.0
Requires-Dist: Flask-Login
Requires-Dist: Flask-SQLAlchemy
Requires-Dist: Flask-Migrate
Requires-Dist: Flask-WTF
Requires-Dist: email-validator
Requires-Dist: python-dotenv
